ec2u/__init__.py
ec2u/cli.py
ec2u/ec2.py
ec2u-0.1.7.dist-info/LICENSE
ec2u-0.1.7.dist-info/METADATA
ec2u-0.1.7.dist-info/WHEEL
ec2u-0.1.7.dist-info/entry_points.txt
ec2u-0.1.7.dist-info/top_level.txt
ec2u-0.1.7.dist-info/RECORD
