Metadata-Version: 2.1
Name: ec2u
Version: 0.1.7
Summary: EC2 Utils
Home-page: https://github.com/nthienan/ec2-utils
Author: An Nguyen
Author-email: nthienan.it@gmail.com
License: MIT
Project-URL: Bug Reports, https://github.com/nthienan/ec2-utils/issues
Project-URL: Source, https://github.com/nthienan/ec2-utils
Keywords: aws,ec2,ec2-utils,ec2u,devops
Platform: UNKNOWN
Classifier: Development Status :: 4 - Beta
Classifier: Intended Audience :: Developers
Classifier: Topic :: Software Development
Classifier: License :: OSI Approved :: MIT License
Classifier: Programming Language :: Python :: 2.7
Classifier: Programming Language :: Python :: 3.8
Requires-Dist: boto3 (==1.4.7)
Requires-Dist: click (==7.1.2)
Requires-Dist: ec2-metadata (==2.2.0)
Requires-Dist: six (==1.12)
